georss_generic_client/__init__.py
georss_generic_client/__version__.py
georss_generic_client/feed.py
georss_generic_client/feed_entry.py
georss_generic_client/feed_manager.py
georss_generic_client-0.8.dist-info/LICENSE
georss_generic_client-0.8.dist-info/METADATA
georss_generic_client-0.8.dist-info/WHEEL
georss_generic_client-0.8.dist-info/top_level.txt
georss_generic_client-0.8.dist-info/RECORD
